bioio_conversion/__init__.py
bioio_conversion/cluster.py
bioio_conversion/bin/cli_batch_convert.py
bioio_conversion/bin/cli_convert.py
bioio_conversion/converters/__init__.py
bioio_conversion/converters/batch_converter.py
bioio_conversion/converters/ome_zarr_converter.py
bioio_conversion-0.2.0.dist-info/licenses/LICENSE
docs/api_reference.rst
docs/conf.py
docs/index.rst
docs/overview.rst
bioio_conversion-0.2.0.dist-info/METADATA
bioio_conversion-0.2.0.dist-info/WHEEL
bioio_conversion-0.2.0.dist-info/entry_points.txt
bioio_conversion-0.2.0.dist-info/top_level.txt
bioio_conversion-0.2.0.dist-info/RECORD
