Metadata-Version: 2.4
Name: bioio-conversion
Version: 0.2.0
Summary: A BioIO conversion tool for going between image formats
Author-email: bioio-devs <brian.whitney@alleninstitute.org>
License: MIT License
Classifier: Development Status :: 4 - Beta
Classifier: Natural Language :: English
Classifier: Programming Language :: Python :: 3.11
Classifier: Programming Language :: Python :: 3.12
Classifier: Programming Language :: Python :: 3.13
Requires-Python: >=3.11
License-File: LICENSE
Requires-Dist: bioio>=3.0.0
Requires-Dist: bioio-ome-zarr>=3.0.1
Requires-Dist: numpy>=1.24.0
Requires-Dist: dask>=2021.10.0
Requires-Dist: numcodecs>=0.10.0
Requires-Dist: scikit-image>=0.19.0
Provides-Extra: lint
Requires-Dist: pre-commit>=2.20.0; extra == "lint"
Provides-Extra: test
Requires-Dist: coverage>=5.1; extra == "test"
Requires-Dist: bioio-ome-tiff>=1.4.0; extra == "test"
Requires-Dist: bioio-czi>=2.4.0; extra == "test"
Requires-Dist: pytest>=5.4.3; extra == "test"
Requires-Dist: pytest-cov>=2.9.0; extra == "test"
Requires-Dist: pytest-raises>=0.11; extra == "test"
Requires-Dist: numpy>=1.24.0; extra == "test"
Provides-Extra: docs
Requires-Dist: gitchangelog>=3.0.4; extra == "docs"
Requires-Dist: Sphinx>=8.0.0; extra == "docs"
Requires-Dist: furo>=2022.4.7; extra == "docs"
Requires-Dist: numpydoc; extra == "docs"
Requires-Dist: sphinx-copybutton; extra == "docs"
Requires-Dist: myst-parser>=1.0; extra == "docs"
Requires-Dist: linkify-it-py>=2.0.0; extra == "docs"
Dynamic: license-file
